Workbook

Sheet OKZ666
F1: FORMATO HOJA DE VIDA DE VEHÍCULOS | T1: Codigo: 09-FR-40
C2: PERSONERÍA DE BOGOTÁ, D. C. | T2: Versión: 03 | V2: Pagina: 1
T3: Vigente desde: 24/10/2019
C6: INFORMACION GENERAL DEL VEHICULO
C7: PLACA | D7: LÍNEA | E7: TIPO | F7: MARCA | H7: COLOR | J7: NÚMERO DE MOTOR | L7: NÚMERO DE CHASIS | M7: CILINDRAJE | N7: SERIE No. | P7: TIPO CARROCERÍA | R7: LICENCIA TRÁNSITO No. | T7: No, DE PASAJEROS | U7: TIPO COMBUSTIBLE:
C8: OKZ666 | D8: DUSTER DYNAMIQUE | E8: WAGON | F8: RENAULT | H8: BLANCO | J8: E412C011375 | L8: 9FBHSR5B6HM294196 | M8: 1998 | N8: 9FBHSR5B6HM294196 | P8: WAGON | R8: 10012891275 | T8: 5 | U8: GASOLINA
I9: CERTIFICADO REVISIÓN TECNICO-MECÁNICA Y DE GASES | P9: INCIDENTES O ACCIDENTES DE TRÁNSITO
C10: Número de poliza | D10: Inicio de vigencia | E10: Fin de vigencia | F10: Número de poliza | G10: Inicio de vigencia | H10: Fin de vigencia | I10: Centro Diagnóstico Autorizado | K10: Inicio de vigencia | L10: Fin de vigencia | N10: Inicio de vigencia | O10: Fin de vigencia | P10: Fecha del evento | Q10: Nombre del Conductor que reporta | T10: Tipo de evento: Incidente ó Accidente
C11: 165054481 | D11: 42683 | E11: 43047
C12: 7.0080015e+15 | D12: 43048 | E12: 43412
C13: 111608895 | D13: 43412 | E13: 43776
C14: 8022168900 | D14: 43777 | E14: 44142
C15: 14730800002070 | D15: 44143 | E15: 44507
C16: 921121000597 | D16: 44508 | E16: 44872
C17: DETALLE DE MANTENIMIENTO PREVENTIVO Y CORRECTIVO
C18: Fecha Novedad de Falla Inspección Diaria Vehicular - I.D.V. ó Revisión Preventiva | D18: Kilometraje (en la fecha de la novedad) | E18: Tipo de novedad reportada en I.D.V. ó Revisión Preventiva | F18: Contrato No. | G18: Proveedor | H18: Kilometraje de la autorización de servicios | I18: Fecha factura | J18: Factura No. | K18: Tipo de mantenimiento | L18: Repuestos y Mano de obra | M18: Cant | N18: Valor Unitario Repuesto | O18: Subtotal Repuestos =(P*Q) | P18: IVA =(R*S) | Q18: Valor total repuesto =(R+S) | R18: Valor Unitario Mano de Obra | S18: Subtotal Mano de obra =(P*U) | T18: IVA (V*W) | U18: Valor total Mano de Obra =(V+W) | V18: Total Facturado =(T+X) | W18: TOTAL FACTURA | X18: DOCUMENTOS SOPORTE
C19: 42976 | H19: 11822 | I19: 42976 | J19: FS7048 | K19: PREVENTIVO | L19: LAVADO GENERAL | M19: 1 | N19: 0 | O19: =+N19*M19 -> 0 | P19: =+O19*0.19 -> 0 | Q19: =+P19+O19 -> 0 | R19: 25210 | S19: =+R19*M19 -> 25210 | T19: =+S19*0.19 -> 4789.9 | U19: =+T19+S19 -> 29999.9 | V19: =+U19+Q19 -> 29999.9
C20: 42948 | H20: 13853 | I20: 42996 | J20: 7166 | K20: PREVENTIVO | L20: LAVADO GENERAL | M20: 1 | N20: 0 | O20: =+N20*M20 -> 0 | P20: =+O20*0.19 -> 0 | Q20: =+P20+O20 -> 0 | R20: 25210 | S20: =+R20*M20 -> 25210 | T20: =+S20*0.19 -> 4789.9 | U20: =+T20+S20 -> 29999.9 | V20: =+U20+Q20 -> 29999.9
N21: 0 | O21: =+N21*M21 -> 0 | P21: =+O21*0.19 -> 0 | Q21: =+P21+O21 -> 0 | R21: 0 | S21: =+R21*M21 -> 0 | T21: =+S21*0.19 -> 0 | U21: =+T21+S21 -> 0 | V21: =+U21+Q21 -> 0
N22: 0 | O22: =+N22*M22 -> 0 | P22: =+O22*0.19 -> 0 | Q22: =+P22+O22 -> 0 | R22: 0 | S22: =+R22*M22 -> 0 | T22: =+S22*0.19 -> 0 | U22: =+T22+S22 -> 0 | V22: =+U22+Q22 -> 0
C23: 42934 | H23: 15477 | I23: 42996 | J23: 7188 | K23: PREVENTIVO | L23: LAVADO EXTERIOR | M23: 1 | N23: 0 | O23: =+N23*M23 -> 0 | P23: =+O23*0.19 -> 0 | Q23: =+P23+O23 -> 0 | R23: 10084 | S23: =+R23*M23 -> 10084 | T23: =+S23*0.19 -> 1915.96 | U23: =+T23+S23 -> 11999.96 | V23: =+U23+Q23 -> 11999.96
N24: 0 | O24: =+N24*M24 -> 0 | P24: =+O24*0.19 -> 0 | Q24: =+P24+O24 -> 0 | R24: 0 | S24: =+R24*M24 -> 0 | T24: =+S24*0.19 -> 0 | U24: =+T24+S24 -> 0 | V24: =+U24+Q24 -> 0
C25: 42951 | H25: 16563 | I25: 42996 | J25: 7203 | K25: PREVENTIVO | L25: LAVADO EXTERIOR | M25: 1 | N25: 0 | O25: =+N25*M25 -> 0 | P25: =+O25*0.19 -> 0 | Q25: =+P25+O25 -> 0 | R25: 10084 | S25: =+R25*M25 -> 10084 | T25: =+S25*0.19 -> 1915.96 | U25: =+T25+S25 -> 11999.96 | V25: =+U25+Q25 -> 11999.96
N26: 0 | O26: =+N26*M26 -> 0 | P26: =+O26*0.19 -> 0 | Q26: =+P26+O26 -> 0 | R26: 0 | S26: =+R26*M26 -> 0 | T26: =+S26*0.19 -> 0 | U26: =+T26+S26 -> 0 | V26: =+U26+Q26 -> 0
H27: 18665 | I27: 43025 | J27: FS 7262 | K27: PREVENTIVO | L27: PLUMILLA LIMPIABRISAS DELANTERA | M27: 2 | N27: 29700 | O27: =+N27*M27 -> 59400 | P27: =+O27*0.19 -> 11286 | Q27: =+P27+O27 -> 70686 | R27: 0 | S27: =+R27*M27 -> 0 | T27: =+S27*0.19 -> 0 | U27: =+T27+S27 -> 0 | V27: =+U27+Q27 -> 70686
H28: 18665 | I28: 43025 | J28: FS 7262 | K28: PREVENTIVO | L28: PLUMILLA LIMPIABRISAS TRASERA | M28: 1 | N28: 27500 | O28: =+N28*M28 -> 27500 | P28: =+O28*0.19 -> 5225 | Q28: =+P28+O28 -> 32725 | R28: 0 | S28: =+R28*M28 -> 0 | T28: =+S28*0.19 -> 0 | U28: =+T28+S28 -> 0 | V28: =+U28+Q28 -> 32725
N29: 0 | O29: =+N29*M29 -> 0 | P29: =+O29*0.19 -> 0 | Q29: =+P29+O29 -> 0 | R29: 0 | S29: =+R29*M29 -> 0 | T29: =+S29*0.19 -> 0 | U29: =+T29+S29 -> 0 | V29: =+U29+Q29 -> 0
H30: 19855 | I30: 43054 | J30: 7415 | K30: PREVENTIVO | L30: LAVADO GENERAL | M30: 1 | N30: 0 | O30: =+N30*M30 -> 0 | P30: =+O30*0.19 -> 0 | Q30: =+P30+O30 -> 0 | R30: 25210 | S30: =+R30*M30 -> 25210 | T30: =+S30*0.19 -> 4789.9 | U30: =+T30+S30 -> 29999.9 | V30: =+U30+Q30 -> 29999.9
H31: 21475 | I31: 43054 | J31: 7432 | K31: PREVENTIVO | L31: LAVADO GENERAL | M31: 1 | N31: 0 | O31: =+N31*M31 -> 0 | P31: =+O31*0.19 -> 0 | Q31: =+P31+O31 -> 0 | R31: 25210 | S31: =+R31*M31 -> 25210 | T31: =+S31*0.19 -> 4789.9 | U31: =+T31+S31 -> 29999.9 | V31: =+U31+Q31 -> 29999.9
H32: 18665 | I32: 43054 | J32: 7405 | K32: PREVENTIVO | L32: LAVADO EXTERIOR | M32: 1 | N32: 0 | O32: =+N32*M32 -> 0 | P32: =+O32*0.19 -> 0 | Q32: =+P32+O32 -> 0 | R32: 10084 | S32: =+R32*M32 -> 10084 | T32: =+S32*0.19 -> 1915.96 | U32: =+T32+S32 -> 11999.96 | V32: =+U32+Q32 -> 11999.96
H33: 19045 | I33: 43054 | J33: 7399 | K33: PREVENTIVO | L33: LAVADO EXTERIOR | M33: 1 | N33: 0 | O33: =+N33*M33 -> 0 | P33: =+O33*0.19 -> 0 | Q33: =+P33+O33 -> 0 | R33: 10084 | S33: =+R33*M33 -> 10084 | T33: =+S33*0.19 -> 1915.96 | U33: =+T33+S33 -> 11999.96 | V33: =+U33+Q33 -> 11999.96
H34: 19045 | I34: 43054 | J34: 7399 | K34: PREVENTIVO | L34: DESPINCHE DE LLANTA | M34: 1 | N34: 0 | O34: =+N34*M34 -> 0 | P34: =+O34*0.19 -> 0 | Q34: =+P34+O34 -> 0 | R34: 12605 | S34: =+R34*M34 -> 12605 | T34: =+S34*0.19 -> 2394.95 | U34: =+T34+S34 -> 14999.95 | V34: =+U34+Q34 -> 14999.95
H35: 23112 | I35: 43082 | J35: 7470 | K35: PREVENTIVO | L35: LAVADO GENERAL | M35: 1 | N35: 0 | O35: =+N35*M35 -> 0 | P35: =+O35*0.19 -> 0 | Q35: =+P35+O35 -> 0 | R35: 25210 | S35: =+R35*M35 -> 25210 | T35: =+S35*0.19 -> 4789.9 | U35: =+T35+S35 -> 29999.9 | V35: =+U35+Q35 -> 29999.9
H36: 24000 | I36: 43070 | J36: 7463 | K36: PREVENTIVO | L36: LAVADO GENERAL | M36: 1 | N36: 0 | O36: =+N36*M36 -> 0 | P36: =+O36*0.19 -> 0 | Q36: =+P36+O36 -> 0 | R36: 25210 | S36: =+R36*M36 -> 25210 | T36: =+S36*0.19 -> 4789.9 | U36: =+T36+S36 -> 29999.9 | V36: =+U36+Q36 -> 29999.9
H37: 26396 | I37: 43150 | J37: 7639 | K37: PREVENTIVO | L37: DESMANCHADO | M37: 1 | N37: 0 | O37: =+N37*M37 -> 0 | P37: =+O37*0.19 -> 0 | Q37: =+P37+O37 -> 0 | R37: 33613 | S37: =+R37*M37 -> 33613 | T37: =+S37*0.19 -> 6386.47 | U37: =+T37+S37 -> 39999.47 | V37: =+U37+Q37 -> 39999.47
H38: 26249 | I38: 43150 | J38: 7635 | K38: PREVENTIVO | L38: LAVADO EXTERIOR | M38: 1 | N38: 0 | O38: =+N38*M38 -> 0 | P38: =+O38*0.19 -> 0 | Q38: =+P38+O38 -> 0 | R38: 10084 | S38: =+R38*M38 -> 10084 | T38: =+S38*0.19 -> 1915.96 | U38: =+T38+S38 -> 11999.96 | V38: =+U38+Q38 -> 11999.96
H39: 29969 | I39: 43220 | J39: 7668 | K39: PREVENTIVO | L39: LAVADO EXTERIOR | M39: 1 | N39: 0 | O39: =+N39*M39 -> 0 | P39: =+O39*0.19 -> 0 | Q39: =+P39+O39 -> 0 | R39: 10084 | S39: =+R39*M39 -> 10084 | T39: =+S39*0.19 -> 1915.96 | U39: =+T39+S39 -> 11999.96 | V39: =+U39+Q39 -> 11999.96
H40: 26749 | I40: 43220 | J40: 7681 | K40: PREVENTIVO | L40: LAVADO MOTOR | M40: 1 | N40: 0 | O40: =+N40*M40 -> 0 | P40: =+O40*0.19 -> 0 | Q40: =+P40+O40 -> 0 | R40: 15126 | S40: =+R40*M40 -> 15126 | T40: =+S40*0.19 -> 2873.94 | U40: =+T40+S40 -> 17999.94 | V40: =+U40+Q40 -> 17999.94
H41: 31828 | I41: 43220 | J41: 7685 | K41: PREVENTIVO | L41: LAVADO EXTERIOR | M41: 1 | N41: 0 | O41: =+N41*M41 -> 0 | P41: =+O41*0.19 -> 0 | Q41: =+P41+O41 -> 0 | R41: 10084 | S41: =+R41*M41 -> 10084 | T41: =+S41*0.19 -> 1915.96 | U41: =+T41+S41 -> 11999.96 | V41: =+U41+Q41 -> 11999.96
... H46: 33830 | I46: 43266 | J46: 7770 | K46: PREVENTIVO | L46: LAVADO EXTERIOR | M46: 1 | N46: 0 | O46: =+N46*M46 -> 0 | P46: =+O46*0.19 -> 0 | Q46: =+P46+O46 -> 0 | R46: 10084 | S46: =+R46*M46 -> 10084 | T46: =+S46*0.19 -> 1915.96 | U46: =+T46+S46 -> 11999.96 | V46: =+U46+Q46 -> 11999.96
H47: 50049 | I47: 43556 | J47: FT 120635 | K47: CORRECTIVO | L47: JUEGO DE PASTILLAS DELANTERAS | M47: 1 | N47: 142941 | O47: =+N47*M47 -> 142941 | P47: =+O47*0.19 -> 27158.79 | Q47: =+P47+O47 -> 170099.79 | R47: 0 | S47: =+R47*M47 -> 0 | T47: =+S47*0.19 -> 0 | U47: =+T47+S47 -> 0 | V47: =+U47+Q47 -> 170099.79
H48: 50049 | I48: 43556 | J48: FT 120635 | K48: CORRECTIVO | L48: JUEGO DE DISCOS DELANTEROS | M48: 1 | N48: 174328 | O48: =+N48*M48 -> 174328 | P48: =+O48*0.19 -> 33122.32 | Q48: =+P48+O48 -> 207450.32 | R48: 0 | S48: =+R48*M48 -> 0 | T48: =+S48*0.19 -> 0 | U48: =+T48+S48 -> 0 | V48: =+U48+Q48 -> 207450.32
H49: 50049 | I49: 43556 | J49: FT 120635 | K49: CORRECTIVO | L49: LIMPIADOR NO CLORATADO DE FRENOS | M49: 1 | N49: 30000 | O49: =+N49*M49 -> 30000 | P49: =+O49*0.19 -> 5700 | Q49: =+P49+O49 -> 35700 | R49: 0 | S49: =+R49*M49 -> 0 | T49: =+S49*0.19 -> 0 | U49: =+T49+S49 -> 0 | V49: =+U49+Q49 -> 35700
H50: 50049 | I50: 43556 | J50: FT 120635 | K50: PREVENTIVO | L50: FILTRO ACEITE | M50: 1 | N50: 25412 | O50: =+N50*M50 -> 25412 | P50: =+O50*0.19 -> 4828.28 | Q50: =+P50+O50 -> 30240.28 | R50: 0 | S50: =+R50*M50 -> 0 | T50: =+S50*0.19 -> 0 | U50: =+T50+S50 -> 0 | V50: =+U50+Q50 -> 30240.28
H51: 50049 | I51: 43556 | J51: FT 120635 | K51: PREVENTIVO | L51: FILTRO AIRE | M51: 1 | N51: 36303 | O51: =+N51*M51 -> 36303 | P51: =+O51*0.19 -> 6897.57 | Q51: =+P51+O51 -> 43200.57 | R51: 0 | S51: =+R51*M51 -> 0 | T51: =+S51*0.19 -> 0 | U51: =+T51+S51 -> 0 | V51: =+U51+Q51 -> 43200.57
H52: 50049 | I52: 43556 | J52: FT 120635 | K52: CORRECTIVO | L52: ACEITE | M52: 6 | N52: 34560 | O52: =+N52*M52 -> 207360 | P52: =+O52*0.19 -> 39398.4 | Q52: =+P52+O52 -> 246758.4 | R52: 0 | S52: =+R52*M52 -> 0 | T52: =+S52*0.19 -> 0 | U52: =+T52+S52 -> 0 | V52: =+U52+Q52 -> 246758.4
H53: 50049 | I53: 43556 | J53: FT 120635 | K53: PREVENTIVO | L53: FILTRO AIRE ACONDICIONADO | M53: 1 | N53: 34622 | O53: =+N53*M53 -> 34622 | P53: =+O53*0.19 -> 6578.18 | Q53: =+P53+O53 -> 41200.18 | R53: 0 | S53: =+R53*M53 -> 0 | T53: =+S53*0.19 -> 0 | U53: =+T53+S53 -> 0 | V53: =+U53+Q53 -> 41200.18
H54: 50049 | I54: 43556 | J54: FT 120635 | K54: CORRECTIVO | L54: REMACHE CON ARANDELA | M54: 30 | N54: 250 | O54: =+N54*M54 -> 7500 | P54: =+O54*0.19 -> 1425 | Q54: =+P54+O54 -> 8925 | R54: 0 | S54: =+R54*M54 -> 0 | T54: =+S54*0.19 -> 0 | U54: =+T54+S54 -> 0 | V54: =+U54+Q54 -> 8925
H55: 50049 | I55: 43556 | J55: FT 120635 | K55: CORRECTIVO | L55: SALPICADERAS | M55: 2 | N55: 26040 | O55: =+N55*M55 -> 52080 | P55: =+O55*0.19 -> 9895.2 | Q55: =+P55+O55 -> 61975.2 | R55: 0 | S55: =+R55*M55 -> 0 | T55: =+S55*0.19 -> 0 | U55: =+T55+S55 -> 0 | V55: =+U55+Q55 -> 61975.2
H56: 50049 | I56: 43556 | J56: FT 120635 | K56: CORRECTIVO | L56: LIQUIDO DE FRENOS | M56: 1 | N56: 11345 | O56: =+N56*M56 -> 11345 | P56: =+O56*0.19 -> 2155.55 | Q56: =+P56+O56 -> 13500.55 | R56: 0 | S56: =+R56*M56 -> 0 | T56: =+S56*0.19 -> 0 | U56: =+T56+S56 -> 0 | V56: =+U56+Q56 -> 13500.55
H57: 50049 | I57: 43556 | J57: FT 120635 | K57: PREVENTIVO | L57: CAMBIO ACEITE MOTOR | M57: 1 | N57: 0 | O57: =+N57*M57 -> 0 | P57: =+O57*0.19 -> 0 | Q57: =+P57+O57 -> 0 | R57: 13801 | S57: =+R57*M57 -> 13801 | T57: =+S57*0.19 -> 2622.19 | U57: =+T57+S57 -> 16423.19 | V57: =+U57+Q57 -> 16423.19
H58: 50049 | I58: 43556 | J58: FT 120635 | K58: CORRECTIVO | L58: CAMBIO FILTRO ACEITE Y AIRE | M58: 1 | N58: 0 | O58: =+N58*M58 -> 0 | P58: =+O58*0.19 -> 0 | Q58: =+P58+O58 -> 0 | R58: 13801 | S58: =+R58*M58 -> 13801 | T58: =+S58*0.19 -> 2622.19 | U58: =+T58+S58 -> 16423.19 | V58: =+U58+Q58 -> 16423.19
... H63: 50049 | I63: 43556 | J63: FT 120635 | K63: CORRECTIVO | L63: INSTALAR SALPICADERAS x4 | M63: 1 | N63: 0 | O63: =+N63*M63 -> 0 | P63: =+O63*0.19 -> 0 | Q63: =+P63+O63 -> 0 | R63: 80000 | S63: =+R63*M63 -> 80000 | T63: =+S63*0.19 -> 15200 | U63: =+T63+S63 -> 95200 | V63: =+U63+Q63 -> 95200
I64: 43395 | J64: FT 119642 | K64: PREVENTIVO | L64: LAVADO GENERAL Y LAVADO MOTOR | M64: 1 | N64: 0 | O64: =+N64*M64 -> 0 | P64: =+O64*0.19 -> 0 | Q64: =+P64+O64 -> 0 | R64: 49160 | S64: =+R64*M64 -> 49160 | T64: =+S64*0.19 -> 9340.4 | U64: =+T64+S64 -> 58500.4 | V64: =+U64+Q64 -> 58500.4
I65: 43395 | J65: FT 119642 | K65: PREVENTIVO | L65: LAVADO GENERAL Y LAVADO MOTOR | M65: 1 | N65: 0 | O65: =+N65*M65 -> 0 | P65: =+O65*0.19 -> 0 | Q65: =+P65+O65 -> 0 | R65: 49160 | S65: =+R65*M65 -> 49160 | T65: =+S65*0.19 -> 9340.4 | U65: =+T65+S65 -> 58500.4 | V65: =+U65+Q65 -> 58500.4
I66: 43610 | J66: FT 120775 | K66: CORRECTIVO | L66: TAPETES UNIVERSAL | M66: 1 | N66: 150000 | O66: =+N66*M66 -> 150000 | P66: =+O66*0.19 -> 28500 | Q66: =+P66+O66 -> 178500 | R66: 0 | S66: =+R66*M66 -> 0 | T66: =+S66*0.19 -> 0 | U66: =+T66+S66 -> 0 | V66: =+U66+Q66 -> 178500
I67: 43610 | J67: FT 120853 | K67: CORRECTIVO | L67: CORREA REPARTICION | M67: 1 | N67: 160639 | O67: =+N67*M67 -> 160639 | P67: =+O67*0.19 -> 30521.41 | Q67: =+P67+O67 -> 191160.41 | R67: 0 | S67: =+R67*M67 -> 0 | T67: =+S67*0.19 -> 0 | U67: =+T67+S67 -> 0 | V67: =+U67+Q67 -> 191160.41
I68: 43610 | J68: FT 120853 | K68: CORRECTIVO | L68: TENSOR REPARTICION | M68: 1 | N68: 85000 | O68: =+N68*M68 -> 85000 | P68: =+O68*0.19 -> 16150 | Q68: =+P68+O68 -> 101150 | R68: 0 | S68: =+R68*M68 -> 0 | T68: =+S68*0.19 -> 0 | U68: =+T68+S68 -> 0 | V68: =+U68+Q68 -> 101150
I69: 43610 | J69: FT 120853 | K69: CORRECTIVO | L69: PATIN | M69: 1 | N69: 60000 | O69: =+N69*M69 -> 60000 | P69: =+O69*0.19 -> 11400 | Q69: =+P69+O69 -> 71400 | R69: 0 | S69: =+R69*M69 -> 0 | T69: =+S69*0.19 -> 0 | U69: =+T69+S69 -> 0 | V69: =+U69+Q69 -> 71400
I70: 43610 | J70: FT 120853 | K70: CORRECTIVO | L70: CAMBIO KIT DE REPARTICION | M70: 1 | N70: 0 | O70: =+N70*M70 -> 0 | P70: =+O70*0.19 -> 0 | Q70: =+P70+O70 -> 0 | R70: 280000 | S70: =+R70*M70 -> 280000 | T70: =+S70*0.19 -> 53200 | U70: =+T70+S70 -> 333200 | V70: =+U70+Q70 -> 333200
I71: 43610 | J71: FT 120853 | K71: CORRECTIVO | L71: BANCO DE PRUEBA CORRECCIÓN DE MEDIDAS | M71: 1 | N71: 0 | O71: =+N71*M71 -> 0 | P71: =+O71*0.19 -> 0 | Q71: =+P71+O71 -> 0 | R71: 500000 | S71: =+R71*M71 -> 500000 | T71: =+S71*0.19 -> 95000 | U71: =+T71+S71 -> 595000 | V71: =+U71+Q71 -> 595000
I72: 43610 | J72: FT 120856 | K72: PREVENTIVO | L72: FILTRO ACEITE | M72: 1 | N72: 25412 | O72: =+N72*M72 -> 25412 | P72: =+O72*0.19 -> 4828.28 | Q72: =+P72+O72 -> 30240.28 | R72: 0 | S72: =+R72*M72 -> 0 | T72: =+S72*0.19 -> 0 | U72: =+T72+S72 -> 0 | V72: =+U72+Q72 -> 30240.28
I73: 43610 | J73: FT 120856 | K73: PREVENTIVO | L73: FILTRO AIRE ACONDICIONADO | M73: 1 | N73: 34622 | O73: =+N73*M73 -> 34622 | P73: =+O73*0.19 -> 6578.18 | Q73: =+P73+O73 -> 41200.18 | R73: 0 | S73: =+R73*M73 -> 0 | T73: =+S73*0.19 -> 0 | U73: =+T73+S73 -> 0 | V73: =+U73+Q73 -> 41200.18
I74: 43610 | J74: FT 120856 | K74: PREVENTIVO | L74: FILTRO AIRE | M74: 1 | N74: 36303 | O74: =+N74*M74 -> 36303 | P74: =+O74*0.19 -> 6897.57 | Q74: =+P74+O74 -> 43200.57 | R74: 0 | S74: =+R74*M74 -> 0 | T74: =+S74*0.19 -> 0 | U74: =+T74+S74 -> 0 | V74: =+U74+Q74 -> 43200.57
I75: 43610 | J75: FT 120856 | K75: CORRECTIVO | L75: JUEGO DE SALPICADERAS | M75: 1 | N75: 100800 | O75: =+N75*M75 -> 100800 | P75: =+O75*0.19 -> 19152 | Q75: =+P75+O75 -> 119952 | R75: 0 | S75: =+R75*M75 -> 0 | T75: =+S75*0.19 -> 0 | U75: =+T75+S75 -> 0 | V75: =+U75+Q75 -> 119952
... I84: 43651 | J84: FT 120917 | K84: PREVENTIVO | L84: LAVADO EXTERIOR | M84: 1 | N84: 0 | O84: =+N84*M84 -> 0 | P84: =+O84*0.19 -> 0 | Q84: =+P84+O84 -> 0 | R84: 18908 | S84: =+R84*M84 -> 18908 | T84: =+S84*0.19 -> 3592.52 | U84: =+T84+S84 -> 22500.52 | V84: =+U84+Q84 -> 22500.52
H85: 56759 | I85: 43668 | J85: FT 120950 | K85: PREVENTIVO | L85: DESPINCHE DE LLANTA | M85: 1 | N85: 0 | O85: =+N85*M85 -> 0 | P85: =+O85*0.19 -> 0 | Q85: =+P85+O85 -> 0 | R85: 16639 | S85: =+R85*M85 -> 16639 | T85: =+S85*0.19 -> 3161.41 | U85: =+T85+S85 -> 19800.41 | V85: =+U85+Q85 -> 19800.41
M86: 0 | N86: 0 | O86: =+N86*M86 -> 0 | P86: =+O86*0.19 -> 0 | Q86: =+P86+O86 -> 0 | R86: 0 | S86: =+R86*M86 -> 0 | T86: =+S86*0.19 -> 0 | U86: =+T86+S86 -> 0 | V86: =+U86+Q86 -> 0
C87: 43852 | H87: 71311 | I87: 43852 | J87: FT 121168 | K87: PREVENTIVO | L87: CAMBIO ACEITE MOTOR | M87: 6 | N87: 29042 | O87: =+N87*M87 -> 174252 | P87: =+O87*0.19 -> 33107.88 | Q87: =+P87+O87 -> 207359.88 | R87: 17941 | S87: =+R87*M87 -> 107646 | T87: =+S87*0.19 -> 20452.74 | U87: =+T87+S87 -> 128098.74 | V87: =+U87+Q87 -> 335458.62
C88: 43852 | H88: 71311 | I88: 43852 | J88: FT 121168 | K88: PREVENTIVO | L88: FILTRO AIRE | M88: 1 | N88: 36303 | O88: =+N88*M88 -> 36303 | P88: =+O88*0.19 -> 6897.57 | Q88: =+P88+O88 -> 43200.57 | R88: 13801 | S88: =+R88*M88 -> 13801 | T88: =+S88*0.19 -> 2622.19 | U88: =+T88+S88 -> 16423.19 | V88: =+U88+Q88 -> 59623.76
C89: 43852 | H89: 71311 | I89: 43852 | J89: FT 121168 | K89: PREVENTIVO | L89: FILTRO ACEITE | M89: 1 | N89: 25412 | O89: =+N89*M89 -> 25412 | P89: =+O89*0.19 -> 4828.28 | Q89: =+P89+O89 -> 30240.28 | R89: 0 | S89: =+R89*M89 -> 0 | T89: =+S89*0.19 -> 0 | U89: =+T89+S89 -> 0 | V89: =+U89+Q89 -> 30240.28
N90: 0 | O90: =+N90*M90 -> 0 | P90: =+O90*0.19 -> 0 | Q90: =+P90+O90 -> 0 | R90: 0 | S90: =+R90*M90 -> 0 | T90: =+S90*0.19 -> 0 | U90: =+T90+S90 -> 0 | V90: =+U90+Q90 -> 0
C91: 43852 | H91: 68262 | I91: 22/0120 | J91: FT121167 | K91: PREVENTIVO | L91: LAVADO GRAL Y MOTOR | M91: 1 | N91: 49160 | O91: =+N91*M91 -> 49160 | P91: =+O91*0.19 -> 9340.4 | Q91: =+P91+O91 -> 58500.4 | R91: 0 | S91: =+R91*M91 -> 0 | T91: =+S91*0.19 -> 0 | U91: =+T91+S91 -> 0 | V91: =+U91+Q91 -> 58500.4
N92: 0 | O92: =+N92*M92 -> 0 | P92: =+O92*0.19 -> 0 | Q92: =+P92+O92 -> 0 | R92: 0 | S92: =+R92*M92 -> 0 | T92: =+S92*0.19 -> 0 | U92: =+T92+S92 -> 0 | V92: =+U92+Q92 -> 0
H93: 76050 | I93: 43944 | J93: FT 121232 | K93: CORRECTIVO | L93: BATERIA | M93: 1 | N93: 301197 | O93: =+N93*M93 -> 301197 | P93: =+O93*0.19 -> 57227.43 | Q93: =+P93+O93 -> 358424.43 | R93: 0 | S93: =+R93*M93 -> 0 | T93: =+S93*0.19 -> 0 | U93: =+T93+S93 -> 0 | V93: =+U93+Q93 -> 358424.43
J94: FT 121232 | K94: CORRECTIVO | L94: CAMBIO DE BATERIA | M94: 1 | N94: 0 | O94: =+N94*M94 -> 0 | P94: =+O94*0.19 -> 0 | Q94: =+P94+O94 -> 0 | R94: 17647 | S94: =+R94*M94 -> 17647 | T94: =+S94*0.19 -> 3352.93 | U94: =+T94+S94 -> 20999.93 | V94: =+U94+Q94 -> 20999.93
J95: FT 121232 | K95: PREVENTIVO | L95: SERVICIO DE SCANER | M95: 1 | N95: 0 | O95: =+N95*M95 -> 0 | P95: =+O95*0.19 -> 0 | Q95: =+P95+O95 -> 0 | R95: 34818 | S95: =+R95*M95 -> 34818 | T95: =+S95*0.19 -> 6615.42 | U95: =+T95+S95 -> 41433.42 | V95: =+U95+Q95 -> 41433.42
H96: 74449 | I96: 43944 | J96: FT 121230 | K96: PREVENTIVO | L96: LAV GRAL Y MOTOR | M96: 1 | N96: 0 | O96: =+N96*M96 -> 0 | P96: =+O96*0.19 -> 0 | Q96: =+P96+O96 -> 0 | R96: 49160 | S96: =+R96*M96 -> 49160 | T96: =+S96*0.19 -> 9340.4 | U96: =+T96+S96 -> 58500.4 | V96: =+U96+Q96 -> 58500.4
G97: INVERSIONES EL NORTE SAS | H97: 84714 | I97: 44095 | J97: FT 7323 | K97: CORRECTIVO | L97: BASES AMORTIGUADOR | M97: 2 | N97: 72000 | O97: =+N97*M97 -> 144000 | P97: =+O97*0.19 -> 27360 | Q97: =+P97+O97 -> 171360 | R97: 70000 | S97: =+R97*M97 -> 140000 | T97: =+S97*0.19 -> 26600 | U97: =+T97+S97 -> 166600 | V97: =+U97+Q97 -> 337960
G98: INVERSIONES EL NORTE SAS | H98: 84714 | I98: 44095 | J98: FT 7323 | K98: PREVENTIVO | L98: JUEGO DE BUJIAS | M98: 1 | N98: 96690 | O98: =+N98*M98 -> 96690 | P98: =+O98*0.19 -> 18371.1 | Q98: =+P98+O98 -> 115061.1 | R98: 86074 | S98: =+R98*M98 -> 86074 | T98: =+S98*0.19 -> 16354.06 | U98: =+T98+S98 -> 102428.06 | V98: =+U98+Q98 -> 217489.16
G99: INVERSIONES EL NORTE SAS | H99: 84714 | I99: 44095 | J99: FT 7323 | K99: PREVENTIVO | L99: FILTRO DE ACEITE | M99: 1 | N99: 21216 | O99: =+N99*M99 -> 21216 | P99: =+O99*0.19 -> 4031.04 | Q99: =+P99+O99 -> 25247.04 | R99: 11965 | S99: =+R99*M99 -> 11965 | T99: =+S99*0.19 -> 2273.35 | U99: =+T99+S99 -> 14238.35 | V99: =+U99+Q99 -> 39485.39
G100: INVERSIONES EL NORTE SAS | H100: 84714 | I100: 44095 | J100: FT 7323 | K100: PREVENTIVO | L100: FILTRO DE AIRE | M100: 1 | N100: 30207 | O100: =+N100*M100 -> 30207 | P100: =+O100*0.19 -> 5739.33 | Q100: =+P100+O100 -> 35946.33 | R100: 10243 | S100: =+R100*M100 -> 10243 | T100: =+S100*0.19 -> 1946.17 | U100: =+T100+S100 -> 12189.17 | V100: =+U100+Q100 -> 48135.5
G101: INVERSIONES EL NORTE SAS | H101: 84714 | I101: 44095 | J101: FT 7323 | K101: PREVENTIVO | L101: LIQUIDO DE FRENOS | M101: 2 | N101: 16074 | O101: =+N101*M101 -> 32148 | P101: =+O101*0.19 -> 6108.12 | Q101: =+P101+O101 -> 38256.12 | R101: 0 | S101: =+R101*M101 -> 0 | T101: =+S101*0.19 -> 0 | U101: =+T101+S101 -> 0 | V101: =+U101+Q101 -> 38256.12
G102: INVERSIONES EL NORTE SAS | H102: 84714 | I102: 44095 | J102: FT 7323 | K102: PREVENTIVO | L102: LIMPIADOR PARA CUERPO DE ACELERACION | M102: 1 | N102: 19469 | O102: =+N102*M102 -> 19469 | P102: =+O102*0.19 -> 3699.11 | Q102: =+P102+O102 -> 23168.11 | R102: 0 | S102: =+R102*M102 -> 0 | T102: =+S102*0.19 -> 0 | U102: =+T102+S102 -> 0 | V102: =+U102+Q102 -> 23168.11
G103: INVERSIONES EL NORTE SAS | H103: 84714 | I103: 44095 | J103: FT 7323 | K103: CORRECTIVO | L103: RODAMIENTO BASE DE AMORTIGUADOR | M103: 2 | N103: 18200 | O103: =+N103*M103 -> 36400 | P103: =+O103*0.19 -> 6916 | Q103: =+P103+O103 -> 43316 | R103: 0 | S103: =+R103*M103 -> 0 | T103: =+S103*0.19 -> 0 | U103: =+T103+S103 -> 0 | V103: =+U103+Q103 -> 43316
G104: INVERSIONES EL NORTE SAS | H104: 84714 | I104: 44095 | J104: FT 7323 | K104: CORRECTIVO | L104: JUEGO PLUMILLAS 20 PULGADAS | M104: 1 | N104: 25365 | O104: =+N104*M104 -> 25365 | P104: =+O104*0.19 -> 4819.35 | Q104: =+P104+O104 -> 30184.35 | R104: 0 | S104: =+R104*M104 -> 0 | T104: =+S104*0.19 -> 0 | U104: =+T104+S104 -> 0 | V104: =+U104+Q104 -> 30184.35
G105: INVERSIONES EL NORTE SAS | H105: 84714 | I105: 44095 | J105: FT 7323 | K105: CORRECTIVO | L105: JUEGO DE AMORTIGUADORES DEL. | M105: 1 | N105: 198261 | O105: =+N105*M105 -> 198261 | P105: =+O105*0.19 -> 37669.59 | Q105: =+P105+O105 -> 235930.59 | R105: 0 | S105: =+R105*M105 -> 0 | T105: =+S105*0.19 -> 0 | U105: =+T105+S105 -> 0 | V105: =+U105+Q105 -> 235930.59
G106: INVERSIONES EL NORTE SAS | H106: 84714 | I106: 44095 | J106: FT 7323 | K106: CORRECTIVO | L106: TUERCA | M106: 1 | N106: 22000 | O106: =+N106*M106 -> 22000 | P106: =+O106*0.19 -> 4180 | Q106: =+P106+O106 -> 26180 | R106: 0 | S106: =+R106*M106 -> 0 | T106: =+S106*0.19 -> 0 | U106: =+T106+S106 -> 0 | V106: =+U106+Q106 -> 26180
G107: INVERSIONES EL NORTE SAS | H107: 84714 | I107: 44095 | J107: FT 7323 | K107: CORRECTIVO | L107: RODAMIENTO SALIDA EJE | M107: 1 | N107: 190000 | O107: =+N107*M107 -> 190000 | P107: =+O107*0.19 -> 36100 | Q107: =+P107+O107 -> 226100 | R107: 90000 | S107: =+R107*M107 -> 90000 | T107: =+S107*0.19 -> 17100 | U107: =+T107+S107 -> 107100 | V107: =+U107+Q107 -> 333200
G108: INVERSIONES EL NORTE SAS | H108: 84714 | I108: 44095 | J108: FT 7323 | K108: CORRECTIVO | L108: RETENEDOR EJE SALIDA | M108: 1 | N108: 50000 | O108: =+N108*M108 -> 50000 | P108: =+O108*0.19 -> 9500 | Q108: =+P108+O108 -> 59500 | R108: 0 | S108: =+R108*M108 -> 0 | T108: =+S108*0.19 -> 0 | U108: =+T108+S108 -> 0 | V108: =+U108+Q108 -> 59500
... G118: INVERSIONES EL NORTE SAS | H118: 84714 | I118: 44095 | J118: FT 7323 | K118: CORRECTIVO | L118: GAS R 134 | M118: 1 | N118: 140000 | O118: =+N118*M118 -> 140000 | P118: =+O118*0.19 -> 26600 | Q118: =+P118+O118 -> 166600 | R118: 0 | S118: =+R118*M118 -> 0 | T118: =+S118*0.19 -> 0 | U118: =+T118+S118 -> 0 | V118: =+U118+Q118 -> 166600
G119: INVERSIONES EL NORTE SAS | H119: 84714 | I119: 44095 | J119: FT 7323 | L119: LAVADO GENERAL Y DESMANCHADO | M119: 1 | N119: 0 | O119: =+N119*M119 -> 0 | P119: =+O119*0.19 -> 0 | Q119: =+P119+O119 -> 0 | R119: 200000 | S119: =+R119*M119 -> 200000 | T119: =+S119*0.19 -> 38000 | U119: =+T119+S119 -> 238000 | V119: =+U119+Q119 -> 238000
G120: INVERSIONES EL NORTE SAS | H120: 84714 | I120: 44095 | J120: FT 7323 | L120: ALINEACION | M120: 1 | N120: 0 | O120: =+N120*M120 -> 0 | P120: =+O120*0.19 -> 0 | Q120: =+P120+O120 -> 0 | R120: 20690 | S120: =+R120*M120 -> 20690 | T120: =+S120*0.19 -> 3931.1 | U120: =+T120+S120 -> 24621.1 | V120: =+U120+Q120 -> 24621.1
G121: INVERSIONES EL NORTE SAS | H121: 84714 | I121: 44095 | J121: FT 7323 | L121: BALANCEO | M121: 4 | N121: 0 | O121: =+N121*M121 -> 0 | P121: =+O121*0.19 -> 0 | Q121: =+P121+O121 -> 0 | R121: 6501 | S121: =+R121*M121 -> 26004 | T121: =+S121*0.19 -> 4940.76 | U121: =+T121+S121 -> 30944.76 | V121: =+U121+Q121 -> 30944.76
G122: INVERSIONES EL NORTE SAS | H122: 84714 | I122: 44095 | J122: FT 7323 | L122: GRASA | M122: 1 | N122: 17385 | O122: =+N122*M122 -> 17385 | P122: =+O122*0.19 -> 3303.15 | Q122: =+P122+O122 -> 20688.15 | R122: 0 | S122: =+R122*M122 -> 0 | T122: =+S122*0.19 -> 0 | U122: =+T122+S122 -> 0 | V122: =+U122+Q122 -> 20688.15
G123: INVERSIONES EL NORTE SAS | H123: 84714 | I123: 44095 | J123: FT 7323 | L123: ACEITE SINTETICO MOTOR | M123: 6 | N123: 22396 | O123: =+N123*M123 -> 134376 | P123: =+O123*0.19 -> 25531.44 | Q123: =+P123+O123 -> 159907.44 | R123: 0 | S123: =+R123*M123 -> 0 | T123: =+S123*0.19 -> 0 | U123: =+T123+S123 -> 0 | V123: =+U123+Q123 -> 159907.44
G124: INVERSIONES EL NORTE SAS | H124: 84714 | I124: 44095 | J124: FT 7323 | L124: PURGA SISTEME DE FRENOS | M124: 1 | N124: 0 | O124: =+N124*M124 -> 0 | P124: =+O124*0.19 -> 0 | Q124: =+P124+O124 -> 0 | R124: 26139 | S124: =+R124*M124 -> 26139 | T124: =+S124*0.19 -> 4966.41 | U124: =+T124+S124 -> 31105.41 | V124: =+U124+Q124 -> 31105.41
G125: INVERSIONES EL NORTE SAS | H125: 84714 | I125: 44095 | J125: FT 7323 | L125: CAMBIO AMORTIGUADOR DELANTERO | M125: 2 | N125: 0 | O125: =+N125*M125 -> 0 | P125: =+O125*0.19 -> 0 | Q125: =+P125+O125 -> 0 | R125: 29039 | S125: =+R125*M125 -> 58078 | T125: =+S125*0.19 -> 11034.82 | U125: =+T125+S125 -> 69112.82 | V125: =+U125+Q125 -> 69112.82
G126: INVERSIONES EL NORTE SAS | H126: 84714 | I126: 44095 | J126: FT 7323 | L126: SERVICIO PRENSA | M126: 1 | N126: 0 | O126: =+N126*M126 -> 0 | P126: =+O126*0.19 -> 0 | Q126: =+P126+O126 -> 0 | R126: 80000 | S126: =+R126*M126 -> 80000 | T126: =+S126*0.19 -> 15200 | U126: =+T126+S126 -> 95200 | V126: =+U126+Q126 -> 95200
G127: INVERSIONES EL NORTE SAS | H127: 84714 | I127: 44095 | J127: FT 7323 | L127: SERVICIO DE ESCANER | M127: 1 | N127: 0 | O127: =+N127*M127 -> 0 | P127: =+O127*0.19 -> 0 | Q127: =+P127+O127 -> 0 | R127: 48710 | S127: =+R127*M127 -> 48710 | T127: =+S127*0.19 -> 9254.9 | U127: =+T127+S127 -> 57964.9 | V127: =+U127+Q127 -> 57964.9
...

Sheet Hoja1
A1: OKZ666 | B1: Repuestos y Mano de obra | C1: Tipo de mantenimiento
A2: TALLERES EL NORTE | B2: ABRAZADERA 450x720 NEGRA | C2: CORRECTIVO
A3: INVERSIONES EL NORTE SAS | B3: ACEITE CHEVRON PARA HIDRAULICO | C3: PREVENTIVO
A4: TALLERES EL NORTE | B4: ACEITE HID ACD PLUS ATF TYPE VI | C4: PREVENTIVO
A5: INVERSIONES EL NORTE SAS | B5: ACEITE HIDRAULICO | C5: PREVENTIVO
A6: INVERSIONES EL NORTE SAS | B6: ACEITE HIDRAULICO CAJA | C6: PREVENTIVO
A7: TALLERES EL NORTE | B7: ACEITE HIDRAULICO DIRECCION | C7: PREVENTIVO
A8: TALLERES EL NORTE | B8: ACEITE MOTOR | C8: PREVENTIVO
A9: TALLERES EL NORTE | B9: ACEITE MOTOR AC DELCO SELE 20W50 | C9: PREVENTIVO
A10: TALLERES EL NORTE | B10: ACEITE SINTETICO | C10: PREVENTIVO
A11: TALLERES EL NORTE | B11: ACEITE SINTETICO 10W40 | C11: PREVENTIVO
A12: INVERSIONES EL NORTE SAS | B12: ACEITE SINTETICO MOTOR | C12: PREVENTIVO
... A385: TALLERES EL NORTE | B385: TORQUEAR SUSPENSION | C385: CORRECTIVO
